README.md
setup.py
cmctl/__init__.py
cmctl/__main__.py
cmctl/talker.py
cmctl.egg-info/PKG-INFO
cmctl.egg-info/SOURCES.txt
cmctl.egg-info/dependency_links.txt
cmctl.egg-info/entry_points.txt
cmctl.egg-info/requires.txt
cmctl.egg-info/top_level.txt