Metadata-Version: 1.1
Name: cmctl
Version: 1.0.6
Summary: Conductometer Control Tool
Home-page: https://github.com/hubpav/cmctl
Author: Pavel Hubner
Author-email: pavel.hubner@gmail.com
License: MIT
Keywords: conductometer,cli,tool
Platform: UNKNOWN
Classifier: Development Status :: 5 - Production/Stable
Classifier: License :: OSI Approved :: MIT License
Classifier: Operating System :: OS Independent
Classifier: Programming Language :: Python
Classifier: Programming Language :: Python :: 3.6
Classifier: Topic :: Scientific/Engineering :: Human Machine Interfaces
Classifier: Environment :: Console
Classifier: Intended Audience :: Science/Research
